kopen_web_shop_flask-7.6.0.dist-info/licenses/LICENSE
trytond/modules/web_shop_flask/__init__.py
trytond/modules/web_shop_flask/exceptions.py
trytond/modules/web_shop_flask/message.xml
trytond/modules/web_shop_flask/migrate_70.py
trytond/modules/web_shop_flask/product.py
trytond/modules/web_shop_flask/product.xml
trytond/modules/web_shop_flask/tryton.cfg
trytond/modules/web_shop_flask/web.py
trytond/modules/web_shop_flask/web.xml
trytond/modules/web_shop_flask/locale/es.po
trytond/modules/web_shop_flask/tests/__init__.py
trytond/modules/web_shop_flask/tests/test_module.py
trytond/modules/web_shop_flask/view/category_form.xml
trytond/modules/web_shop_flask/view/payment_method_form.xml
trytond/modules/web_shop_flask/view/payment_method_list.xml
trytond/modules/web_shop_flask/view/shop_form.xml
trytond/modules/web_shop_flask/view/template_form.xml
kopen_web_shop_flask-7.6.0.dist-info/METADATA
kopen_web_shop_flask-7.6.0.dist-info/WHEEL
kopen_web_shop_flask-7.6.0.dist-info/entry_points.txt
kopen_web_shop_flask-7.6.0.dist-info/top_level.txt
kopen_web_shop_flask-7.6.0.dist-info/RECORD
