Metadata-Version: 2.4
Name: kopen_web_shop_flask
Version: 7.6.0
Summary: Tryton module to use as backend for custom Flask Webshop
Home-page: https://www.kopen.es
Author: KOPEN SOFTWARE, SLU
Author-email: info@kopen.es
License: GPL-3
Keywords: tryton flask webshop
Classifier: Development Status :: 5 - Production/Stable
Classifier: Environment :: Plugins
Classifier: Framework :: Tryton
Classifier: Intended Audience :: Developers
Classifier: Intended Audience :: Financial and Insurance Industry
Classifier: Intended Audience :: Legal Industry
Classifier: License :: OSI Approved :: GNU General Public License v3 or later (GPLv3+)
Classifier: Natural Language :: Catalan
Classifier: Natural Language :: English
Classifier: Natural Language :: Spanish
Classifier: Operating System :: OS Independent
Classifier: Programming Language :: Python :: 3
Classifier: Programming Language :: Python :: 3.8
Classifier: Programming Language :: Python :: 3.9
Classifier: Programming Language :: Python :: 3.10
Classifier: Programming Language :: Python :: 3.11
Classifier: Programming Language :: Python :: 3.12
Classifier: Programming Language :: Python :: Implementation :: CPython
Classifier: Programming Language :: Python :: Implementation :: PyPy
Classifier: Topic :: Office/Business
Requires-Python: >=3.8
License-File: LICENSE
Requires-Dist: trytond_party<7.7,>=7.6
Requires-Dist: trytond_product<7.7,>=7.6
Requires-Dist: trytond_product_image<7.7,>=7.6
Requires-Dist: trytond_sale<7.7,>=7.6
Requires-Dist: trytond_web_shop<7.7,>=7.6
Requires-Dist: trytond_web_user<7.7,>=7.6
Requires-Dist: trytond<7.7,>=7.6
Provides-Extra: test
Requires-Dist: proteus<7.7,>=7.6; extra == "test"
Requires-Dist: trytond_account_payment<7.7,>=7.6; extra == "test"
Dynamic: author
Dynamic: author-email
Dynamic: classifier
Dynamic: description
Dynamic: description-content-type
Dynamic: home-page
Dynamic: keywords
Dynamic: license
Dynamic: license-file
Dynamic: provides-extra
Dynamic: requires-dist
Dynamic: requires-python
Dynamic: summary
